odoo10_addon_apps_product_creator-10.0.1.0.0.99.dev34-py2.7-nspkg.pth
odoo/addons/apps_product_creator/README.rst
odoo/addons/apps_product_creator/__init__.py
odoo/addons/apps_product_creator/__manifest__.py
odoo/addons/apps_product_creator/data/ir_cron.xml
odoo/addons/apps_product_creator/data/product_attribute.xml
odoo/addons/apps_product_creator/i18n/apps_product_creator.pot
odoo/addons/apps_product_creator/i18n/es.po
odoo/addons/apps_product_creator/i18n/fr.po
odoo/addons/apps_product_creator/i18n/it.po
odoo/addons/apps_product_creator/models/__init__.py
odoo/addons/apps_product_creator/models/odoo_module.py
odoo/addons/apps_product_creator/models/product_product.py
odoo/addons/apps_product_creator/models/product_template.py
odoo/addons/apps_product_creator/static/description/icon.png
odoo/addons/apps_product_creator/tests/__init__.py
odoo/addons/apps_product_creator/tests/test_apps_product_creator.py
odoo/addons/apps_product_creator/views/view_odoo_module.xml
odoo/addons/apps_product_creator/views/view_product_product.xml
odoo10_addon_apps_product_creator-10.0.1.0.0.99.dev34.dist-info/METADATA
odoo10_addon_apps_product_creator-10.0.1.0.0.99.dev34.dist-info/RECORD
odoo10_addon_apps_product_creator-10.0.1.0.0.99.dev34.dist-info/WHEEL
odoo10_addon_apps_product_creator-10.0.1.0.0.99.dev34.dist-info/namespace_packages.txt
odoo10_addon_apps_product_creator-10.0.1.0.0.99.dev34.dist-info/top_level.txt
